MANIFEST.in
setup.py
wizard_interface/CommonTool.py
wizard_interface/DataBaseTool.py
wizard_interface/InternetTool.py
wizard_interface/ToolFactory.py
wizard_interface/__init__.py
wizard_interface.egg-info/PKG-INFO
wizard_interface.egg-info/SOURCES.txt
wizard_interface.egg-info/dependency_links.txt
wizard_interface.egg-info/requires.txt
wizard_interface.egg-info/top_level.txt