Metadata-Version: 1.0
Name: wizard-interface
Version: 1.0.4
Summary: interface test, python, open sourced
Home-page: http://wizard.ren
Author: Jie Yang
Author-email: chnyangjie@gmail.com
License: MIT
Platform: UNKNOWN
